AutoUpdate/AutoUpdate.py
AutoUpdate/__init__.py
AutoUpdate-0.0.2.dist-info/LICENSE.txt
AutoUpdate-0.0.2.dist-info/METADATA
AutoUpdate-0.0.2.dist-info/WHEEL
AutoUpdate-0.0.2.dist-info/top_level.txt
AutoUpdate-0.0.2.dist-info/RECORD
