Metadata-Version: 2.1
Name: AutoUpdate
Version: 0.0.2
Summary: Check for updates in the easiest way possible.
Home-page: https://bruhdev.com
Author: BruhDev
Author-email: mr.bruh.dev@gmail.com
License: UNKNOWN
Platform: UNKNOWN
Requires-Python: >=3.6
